hebo/__init__.py
hebo/mindspore.py
hebo/sklearn_tuner.py
hebo/acq_optimizers/__init__.py
hebo/acq_optimizers/evolution_optimizer.py
hebo/acquisitions/__init__.py
hebo/acquisitions/acq.py
hebo/design_space/__init__.py
hebo/design_space/bool_param.py
hebo/design_space/categorical_param.py
hebo/design_space/design_space.py
hebo/design_space/int_exponent_param.py
hebo/design_space/integer_param.py
hebo/design_space/numeric_param.py
hebo/design_space/param.py
hebo/design_space/pow_integer_param.py
hebo/design_space/pow_param.py
hebo/design_space/step_int.py
hebo/models/__init__.py
hebo/models/base_model.py
hebo/models/layers.py
hebo/models/model_factory.py
hebo/models/scalers.py
hebo/models/util.py
hebo/models/gp/__init__.py
hebo/models/gp/gpy_mlp.py
hebo/models/gp/gpy_wgp.py
hebo/models/rf/__init__.py
hebo/models/rf/rf.py
hebo/optimizers/__init__.py
hebo/optimizers/abstract_optimizer.py
hebo/optimizers/hebo.py
hebo/optimizers/util.py
test/__init__.py
test/test_acq.py
test/test_base_model.py
test/test_categorical_encoder.py
test/test_constrained_multi_objective.py
test/test_design_space.py
test/test_evolution_optimizer.py
test/test_model_util.py
test/test_optimizer.py
test/test_scalers.py
test/test_sklearn_tuner.py
HEBO_mindspore-0.2.1.dist-info/LICENSE
HEBO_mindspore-0.2.1.dist-info/METADATA
HEBO_mindspore-0.2.1.dist-info/WHEEL
HEBO_mindspore-0.2.1.dist-info/top_level.txt
HEBO_mindspore-0.2.1.dist-info/RECORD
