Metadata-Version: 2.1
Name: HEBO-mindspore
Version: 0.2.1
Summary: Heteroscedastic evolutionary bayesian optimisation
Home-page: https://github.com/huawei-noah/noah-research/tree/mindspore/HEBO_mindspore
License: UNKNOWN
Platform: UNKNOWN
Requires-Dist: numpy (>=1.15)
Requires-Dist: pandas (>=1.0.1)
Requires-Dist: pymoo (>=0.4.1)
Requires-Dist: scikit-learn (>=0.22)
Requires-Dist: GPy (==1.9.9)
Requires-Dist: pyDOE2
Requires-Dist: mindspore (>=1.2.0)
